s3wm/__init__.py
s3wm/layouts/__init__.py
s3wm/layouts/default_tile/__init__.py
s3wm/layouts/default_tile/key_bindings.py
s3wm/layouts/default_tile/layout.py
s3wm/layouts/default_tile/tab.py
s3wm/main.py
s3wm/s3wm.py
s3wm/tests/__init__.py
s3wm/tests/test_stub.py
s3wm_core/__init__.py
s3wm_core/key_combination.py
s3wm_core/keymap.py
s3wm_core/layout_base.py
s3wm_core/s3screen.py
s3wm_core/s3window.py
s3wm_core/utils.py
s3wm_core/wm_config.py
s3wm_core/x_models.py
s3wm-0.2.3.dist-info/entry_points.txt
s3wm-0.2.3.dist-info/WHEEL
s3wm-0.2.3.dist-info/METADATA
s3wm-0.2.3.dist-info/RECORD
